trytond/modules/lang_extension/README.rst
trytond/modules/lang_extension/__init__.py
trytond/modules/lang_extension/lang.xml
trytond/modules/lang_extension/tryton.cfg
trytond/modules/lang_extension/locale/de.po
mds_lang_extension-5.0.0.dist-info/METADATA
mds_lang_extension-5.0.0.dist-info/WHEEL
mds_lang_extension-5.0.0.dist-info/entry_points.txt
mds_lang_extension-5.0.0.dist-info/top_level.txt
mds_lang_extension-5.0.0.dist-info/RECORD
